I2C_slavefinal.v
module i2c_slave(
    input wire clk,           // System clock
    input wire rst,           // Reset signal
    input wire scl,           // I2C Clock Line
    inout wire sda,           // I2C Data Line (Bidirectional)
    output reg [7:0] data_out, // Received Data Output
    output reg ack_out        // Acknowledge signal to master
);

    reg [6:0] slave_address = 7'b1010001; // Set your Slave Address
    reg [7:0] received_data;
    reg [3:0] bit_count;       // Bit counter for data reception
    reg sda_out;               // Internal SDA output buffer
    reg sda_en;                // Enable signal for SDA control

    assign sda = (sda_en) ? sda_out : 1'bz; // Tri-state buffer for SDA

    // State Encoding using Parameters
    parameter IDLE          = 3'b000;
    parameter ADDRESS_MATCH = 3'b001;
    parameter ACK_ADDRESS   = 3'b010;
    parameter RECEIVING     = 3'b011;
    parameter ACK_DATA      = 3'b100;

    reg [2:0] state;

    always @(negedge scl or posedge rst) begin
        if (rst) begin
            state <= IDLE;
            received_data <= 8'b0;
            bit_count <= 0;
            sda_en <= 0;
            ack_out <= 0;
            data_out <= 8'b0;
        end else begin
            case (state)
                IDLE: begin
                    bit_count <= 0;
                    ack_out <= 0;
                    if (sda == 0) // Start condition detected (SDA goes low while SCL is high)
                        state <= ADDRESS_MATCH;
                end

                ADDRESS_MATCH: begin
                    received_data[6:0] <= {received_data[5:0], sda}; // Shift SDA into address buffer
                    bit_count <= bit_count + 1;
                    if (bit_count == 6) // After receiving 7 address bits
                        state <= ACK_ADDRESS;
                end

                ACK_ADDRESS: begin
                    if (received_data[6:0] == slave_address) begin
                        sda_en <= 1;  // Enable SDA to send ACK
                        sda_out <= 0; // Send ACK (pull SDA low)
                        ack_out <= 1; // Indicate ACK sent to master
                        state <= RECEIVING;
                    end else begin
                        state <= IDLE; // Address mismatch, return to IDLE
                    end
                    bit_count <= 0;
                end

                RECEIVING: begin
                    received_data <= {received_data[6:0], sda}; // Shift SDA into received_data
                    bit_count <= bit_count + 1;
                    if (bit_count == 7) // After receiving 8 bits
                        state <= ACK_DATA;
                end

                ACK_DATA: begin
                    sda_en <= 1;  // Enable SDA to send ACK
                    sda_out <= 0; // Send ACK (pull SDA low)
                    ack_out <= 1; // Indicate ACK sent to master
                    data_out <= received_data; // Store received data
                    state <= IDLE; // Go back to IDLE for next transaction
                end

                default: state <= IDLE;
            endcase
        end
    end

endmodule

I2C_masterfinal.v
module i2c_master (
    input wire clk,         // System clock
    input wire rst,         // Reset
    input wire start,       // Start signal
    input wire [7:0] data,  // Data to send
    input wire [6:0] addr,  // Slave address
    input wire rw,          // Read (1) / Write (0)
    output reg scl,         // Clock signal
    inout wire sda,         // Bidirectional data line
    output reg busy         // Indicates if I2C is busy
);

    reg [3:0] state;
    reg [7:0] shift_reg;
    reg sda_out;
    reg sda_en;  // Controls SDA as output

    assign sda = (sda_en) ? sda_out : 1'bz; // Tri-state buffer for bidirectional line

    // I2C states
    localparam IDLE = 0, START = 1, ADDRESS = 2, ACK = 3, DATA = 4, STOP = 5;

    always @(posedge clk or posedge rst) begin
        if (rst) begin
            state <= IDLE;
            scl <= 1;
            sda_out <= 1;
            sda_en <= 0;
            busy <= 0;
        end else begin
            case (state)
                IDLE: begin
                    if (start) begin
                        state <= START;
                        busy <= 1;
                        //scl<=~scl; #5;
                    end
                end
                START: begin
                    sda_out <= 0; // Start condition: SDA low while SCL is high
                    sda_en <= 1;
                    state <= ADDRESS;
                end
                ADDRESS: begin
                    shift_reg <= {addr, rw}; // Load address and R/W bit
                    sda_out <= shift_reg[7]; // Send MSB first
                    state <= ACK;
                end
                ACK: begin
                    sda_en <= 0; // Release SDA for slave ACK
                    state <= DATA;
                end
                DATA: begin
                    shift_reg <= data;
                    sda_out <= shift_reg[7];
                    sda_en <= 1;
                    state <= STOP;
                end
                STOP: begin
                    sda_out <= 1; // Stop condition: SDA goes high while SCL is high
                    sda_en <= 0;
                    state <= IDLE;
                    busy <= 0;
                end
            endcase
        end
    end
endmodule

I2C_testfinal.v
`timescale 1ms/1ns

module i2c_tb;

    reg clk, rst, start;
    reg [6:0] addr; // 7-bit I2C address
    reg rw;         // Read (1) or Write (0)
    reg [7:0] data; // Data to send
    wire sda, scl, busy;
    wire [7:0] received_data;

    // Instantiate the I2C Master
    i2c_master master (
        .clk(clk),
        .rst(rst),
        .start(start),
        .addr(addr),
        .rw(rw),
        .scl(scl),
        .sda(sda),
        .busy(busy),
        .data(data)
    );

    // Instantiate the I2C Slave
    i2c_slave slave (
        .clk(clk),
        .rst(rst),
        .scl(scl),
        .sda(sda),
        .data_out(received_data)
    );

    // Clock Generation
    always #10 clk = ~clk; // 10ns period (100MHz clock)

    // Simulation Process
    initial begin
        // Open VCD file for GTKWave
        $dumpfile("i2c_waveform.vcd"); 
        $dumpvars(0, i2c_tb);

        // Initialize signals
        clk = 0;
        rst = 1;
        start = 0;
        addr = 7'b1010001; // Example Slave Address
        rw = 0;            // Write operation
        data = 8'h00;      // Data to send

        #20 rst = 0;  // De-assert reset
        #50 start = 1; // Start I2C transaction
        #20 start = 0;

        // Wait for transaction to complete
        wait (busy == 0);
        
        #100; // Hold for some time
        $display("Received Data: %h",received_data);
        $finish;
    end

endmodule

i2c_waveform.vcd
$date
	Sun Aug 02 14:02:05 2026
$end
$version
	Icarus Verilog
$end
$timescale
	1ns
$end
$scope module i2c_tb $end
$var wire 1 ! sda $end
$var wire 1 " scl $end
$var wire 8 # received_data [7:0] $end
$var wire 1 $ busy $end
$var reg 7 % addr [6:0] $end
$var reg 1 & clk $end
$var reg 8 ' data [7:0] $end
$var reg 1 ( rst $end
$var reg 1 ) rw $end
$var reg 1 * start $end
$scope module master $end
$var wire 7 + addr [6:0] $end
$var wire 1 & clk $end
$var wire 8 , data [7:0] $end
$var wire 1 ( rst $end
$var wire 1 ) rw $end
$var wire 1 ! sda $end
$var wire 1 * start $end
$var parameter 32 - ACK $end
$var parameter 32 . ADDRESS $end
$var parameter 32 / DATA $end
$var parameter 32 0 IDLE $end
$var parameter 32 1 START $end
$var parameter 32 2 STOP $end
$var reg 1 $ busy $end
$var reg 1 " scl $end
$var reg 1 3 sda_en $end
$var reg 1 4 sda_out $end
$var reg 8 5 shift_reg [7:0] $end
$var reg 4 6 state [3:0] $end
$upscope $end
$scope module slave $end
$var wire 1 & clk $end
$var wire 1 ( rst $end
$var wire 1 " scl $end
$var wire 1 ! sda $end
$var parameter 3 7 ACK_ADDRESS $end
$var parameter 3 8 ACK_DATA $end
$var parameter 3 9 ADDRESS_MATCH $end
$var parameter 3 : IDLE $end
$var parameter 3 ; RECEIVING $end
$var reg 1 < ack_out $end
$var reg 4 = bit_count [3:0] $end
$var reg 8 > data_out [7:0] $end
$var reg 8 ? received_data [7:0] $end
$var reg 1 @ sda_en $end
$var reg 1 A sda_out $end
$var reg 7 B slave_address [6:0] $end
$var reg 3 C state [2:0] $end
$upscope $end
$upscope $end
$enddefinitions $end
$comment Show the parameter values. $end
$dumpall
b11 ;
b0 :
b1 9
b100 8
b10 7
b101 2
b1 1
b0 0
b100 /
b10 .
b11 -
$end
#0
$dumpvars
b0 C
b1010001 B
xA
0@
b0 ?
b0 >
b0 =
0<
b0 6
bx 5
14
03
b0 ,
b1010001 +
0*
0)
1(
b0 '
0&
b1010001 %
0$
b0 #
1"
z!
$end
#10000000
1&
#20000000
0&
0(
#30000000
1&
#40000000
0&
#50000000
1&
#60000000
0&
#70000000
1$
b1 6
1&
1*
#80000000
0&
#90000000
0!
b10 6
13
04
1&
0*
#100000000
0&
#110000000
x!
b11 6
x4
b10100010 5
1&
#120000000
0&
#130000000
z!
b100 6
03
1&
#140000000
0&
#150000000
1!
b101 6
13
14
b0 5
1&
#160000000
0&
#170000000
z!
0$
b0 6
03
1&
